LICENSE
README.rst
setup.py
vk_air/__init__.py
vk_air/attachment.py
vk_air/bot_api.py
vk_air/client.py
vk_air/enums.py
vk_air/keyboard.py
vk_air/longpoll.py
vk_air/template.py
vk_air/utils.py
vk_air.egg-info/PKG-INFO
vk_air.egg-info/SOURCES.txt
vk_air.egg-info/dependency_links.txt
vk_air.egg-info/top_level.txt
vk_air/objects/__init__.py
vk_air/objects/album.py
vk_air/objects/app.py
vk_air/objects/audio.py
vk_air/objects/background.py
vk_air/objects/ban.py
vk_air/objects/board.py
vk_air/objects/button.py
vk_air/objects/callback.py
vk_air/objects/career.py
vk_air/objects/changes.py
vk_air/objects/chat.py
vk_air/objects/city.py
vk_air/objects/comment.py
vk_air/objects/connections.py
vk_air/objects/contact.py
vk_air/objects/conversation.py
vk_air/objects/counters.py
vk_air/objects/country.py
vk_air/objects/cover.py
vk_air/objects/currency.py
vk_air/objects/delivery.py
vk_air/objects/doc.py
vk_air/objects/donut.py
vk_air/objects/education.py
vk_air/objects/enumsobj.py
vk_air/objects/eventobj.py
vk_air/objects/geo.py
vk_air/objects/gift.py
vk_air/objects/gradient.py
vk_air/objects/group.py
vk_air/objects/history.py
vk_air/objects/link.py
vk_air/objects/lp.py
vk_air/objects/market.py
vk_air/objects/message.py
vk_air/objects/military.py
vk_air/objects/note.py
vk_air/objects/occupation.py
vk_air/objects/officer.py
vk_air/objects/online.py
vk_air/objects/order.py
vk_air/objects/page.py
vk_air/objects/personal.py
vk_air/objects/photo.py
vk_air/objects/place.py
vk_air/objects/poll.py
vk_air/objects/postedphoto.py
vk_air/objects/pretty.py
vk_air/objects/product.py
vk_air/objects/recipient.py
vk_air/objects/server.py
vk_air/objects/settings.py
vk_air/objects/sticker.py
vk_air/objects/storage.py
vk_air/objects/stories.py
vk_air/objects/tags.py
vk_air/objects/user.py
vk_air/objects/variant.py
vk_air/objects/video.py
vk_air/objects/vkpay.py
vk_air/objects/wall.py